{
    "monte_verde_mg": {
        "id": "monte_verde_mg",
        "name": "Monte Verde",
        "recentChange": 0.1591,
        "timeline": [
            4.4,
            4.0,
            3.6,
            3.7,
            3.6,
            5.1,
            5.0,
            4.5
        ],
        "weather": {
            "daily": [
                {
                    "max": 20,
                    "cond": "Estável"
                },
                {
                    "max": 20,
                    "cond": "Estável"
                },
                {
                    "max": 20,
                    "cond": "Estável"
                },
                {
                    "max": 20,
                    "cond": "Estável"
                },
                {
                    "max": 20,
                    "cond": "Estável"
                },
                {
                    "max": 20,
                    "cond": "Estável"
                },
                {
                    "max": 20,
                    "cond": "Estável"
                }
            ]
        },
        "insight": "Demanda por Monte Verde segue em alta."
    },
    "campos_do_jordao_sp": {
        "id": "campos_do_jordao_sp",
        "name": "Campos do Jordão",
        "recentChange": 0.1308,
        "timeline": [
            68.1,
            54.6,
            56.0,
            56.7,
            60.0,
            81.1,
            80.4,
            65.5
        ],
        "weather": {
            "daily": [
                {
                    "max": 20,
                    "cond": "Estável"
                },
                {
                    "max": 20,
                    "cond": "Estável"
                },
                {
                    "max": 20,
                    "cond": "Estável"
                },
                {
                    "max": 20,
                    "cond": "Estável"
                },
                {
                    "max": 20,
                    "cond": "Estável"
                },
                {
                    "max": 20,
                    "cond": "Estável"
                },
                {
                    "max": 20,
                    "cond": "Estável"
                }
            ]
        },
        "insight": "Campos do Jordão apresenta comportamento em alta."
    },
    "gramado_canela_rs": {
        "id": "gramado_canela_rs",
        "name": "Gramado + Canela",
        "recentChange": -0.0723,
        "timeline": [
            10.0,
            10.1,
            9.1,
            11.1,
            10.4,
            13.4,
            11.6,
            10.5
        ],
        "weather": {
            "daily": [
                {
                    "max": 20,
                    "cond": "Estável"
                },
                {
                    "max": 20,
                    "cond": "Estável"
                },
                {
                    "max": 20,
                    "cond": "Estável"
                },
                {
                    "max": 20,
                    "cond": "Estável"
                },
                {
                    "max": 20,
                    "cond": "Estável"
                },
                {
                    "max": 20,
                    "cond": "Estável"
                },
                {
                    "max": 20,
                    "cond": "Estável"
                }
            ]
        },
        "insight": "Serra Gaúcha estável."
    },
    "sao_lourenco_mg": {
        "id": "sao_lourenco_mg",
        "name": "São Lourenço",
        "recentChange": 0.1942,
        "timeline": [
            5.0,
            4.4,
            4.3,
            3.9,
            4.6,
            5.7,
            6.1,
            5.0
        ],
        "weather": {
            "daily": [
                {
                    "max": 20,
                    "cond": "Estável"
                },
                {
                    "max": 20,
                    "cond": "Estável"
                },
                {
                    "max": 20,
                    "cond": "Estável"
                },
                {
                    "max": 20,
                    "cond": "Estável"
                },
                {
                    "max": 20,
                    "cond": "Estável"
                },
                {
                    "max": 20,
                    "cond": "Estável"
                },
                {
                    "max": 20,
                    "cond": "Estável"
                }
            ]
        },
        "insight": "São Lourenço em alta."
    },
    "pocos_de_caldas_mg": {
        "id": "pocos_de_caldas_mg",
        "name": "Poços de Caldas",
        "recentChange": 0.0321,
        "timeline": [
            63.0,
            57.6,
            61.6,
            62.6,
            63.7,
            70.4,
            72.1,
            66.5
        ],
        "weather": {
            "daily": [
                {
                    "max": 20,
                    "cond": "Estável"
                },
                {
                    "max": 20,
                    "cond": "Estável"
                },
                {
                    "max": 20,
                    "cond": "Estável"
                },
                {
                    "max": 20,
                    "cond": "Estável"
                },
                {
                    "max": 20,
                    "cond": "Estável"
                },
                {
                    "max": 20,
                    "cond": "Estável"
                },
                {
                    "max": 20,
                    "cond": "Estável"
                }
            ]
        },
        "insight": "Poços em alta."
    },
    "sao_bento_sapucai_sp": {
        "id": "sao_bento_sapucai_sp",
        "name": "São Bento do Sapucaí",
        "recentChange": 0.8138,
        "timeline": [
            32.0,
            18.0,
            7.3,
            6.9,
            25.9,
            51.0,
            73.0,
            46.0
        ],
        "weather": {
            "daily": [
                {
                    "max": 20,
                    "cond": "Estável"
                },
                {
                    "max": 20,
                    "cond": "Estável"
                },
                {
                    "max": 20,
                    "cond": "Estável"
                },
                {
                    "max": 20,
                    "cond": "Estável"
                },
                {
                    "max": 20,
                    "cond": "Estável"
                },
                {
                    "max": 20,
                    "cond": "Estável"
                },
                {
                    "max": 20,
                    "cond": "Estável"
                }
            ]
        },
        "insight": "São Bento em alta."
    },
    "passa_quatro_mg": {
        "id": "passa_quatro_mg",
        "name": "Passa Quatro",
        "recentChange": 1.1302,
        "timeline": [
            22.4,
            0.1,
            0.1,
            9.9,
            0.1,
            44.7,
            56.4,
            45.0
        ],
        "weather": {
            "daily": [
                {
                    "max": 20,
                    "cond": "Estável"
                },
                {
                    "max": 20,
                    "cond": "Estável"
                },
                {
                    "max": 20,
                    "cond": "Estável"
                },
                {
                    "max": 20,
                    "cond": "Estável"
                },
                {
                    "max": 20,
                    "cond": "Estável"
                },
                {
                    "max": 20,
                    "cond": "Estável"
                },
                {
                    "max": 20,
                    "cond": "Estável"
                }
            ]
        },
        "insight": "Passa Quatro em alta."
    },
    "serra_negra_sp": {
        "id": "serra_negra_sp",
        "name": "Serra Negra",
        "recentChange": 0.4243,
        "timeline": [
            69.3,
            46.3,
            56.3,
            41.1,
            47.0,
            75.7,
            83.4,
            85.5
        ],
        "weather": {
            "daily": [
                {
                    "max": 20,
                    "cond": "Estável"
                },
                {
                    "max": 20,
                    "cond": "Estável"
                },
                {
                    "max": 20,
                    "cond": "Estável"
                },
                {
                    "max": 20,
                    "cond": "Estável"
                },
                {
                    "max": 20,
                    "cond": "Estável"
                },
                {
                    "max": 20,
                    "cond": "Estável"
                },
                {
                    "max": 20,
                    "cond": "Estável"
                }
            ]
        },
        "insight": "Serra Negra em alta."
    },
    "goncalves_mg": {
        "id": "goncalves_mg",
        "name": "Gonçalves",
        "recentChange": 0.248,
        "timeline": [
            55.4,
            38.9,
            49.4,
            38.9,
            48.9,
            65.7,
            66.9,
            65.5
        ],
        "weather": {
            "daily": [
                {
                    "max": 20,
                    "cond": "Estável"
                },
                {
                    "max": 20,
                    "cond": "Estável"
                },
                {
                    "max": 20,
                    "cond": "Estável"
                },
                {
                    "max": 20,
                    "cond": "Estável"
                },
                {
                    "max": 20,
                    "cond": "Estável"
                },
                {
                    "max": 20,
                    "cond": "Estável"
                },
                {
                    "max": 20,
                    "cond": "Estável"
                }
            ]
        },
        "insight": "Gonçalves em alta."
    }
}